mp3_autotagger/__init__.py
mp3_autotagger/__main__.py
mp3_autotagger/assets/autotagger_icon.png
mp3_autotagger/assets/main_icon.icns
mp3_autotagger/assets/main_icon.ico
mp3_autotagger/assets/main_icon.png
mp3_autotagger/assets/no_cover.jpg
mp3_autotagger/assets/youtube2mp3_icon.png
mp3_autotagger/gui/__init__.py
mp3_autotagger/gui/main_window.py
mp3_autotagger/gui/mp3_autotagger_tab.py
mp3_autotagger/gui/ui.py
mp3_autotagger/gui/youtube2mp3_tab.py
mp3_autotagger/main.py
mp3_autotagger/translations/eng-es.qm
mp3_autotagger/translations/eng-es.ts
mp3_autotagger/utils/assets.py
mp3_autotagger/utils/mp3.py
mp3_autotagger/utils/package.py
mp3_autotagger/utils/qt.py
mp3_autotagger/utils/shazam.py
mp3_autotagger/utils/system.py
mp3_autotagger/utils/update.py
mp3_autotagger/utils/youtube.py
mp3_autotagger-1.2.2.dist-info/LICENSE
mp3_autotagger-1.2.2.dist-info/METADATA
mp3_autotagger-1.2.2.dist-info/NOTICES.md
mp3_autotagger-1.2.2.dist-info/WHEEL
mp3_autotagger-1.2.2.dist-info/entry_points.txt
mp3_autotagger-1.2.2.dist-info/RECORD
