Metadata-Version: 2.3
Name: mp3-autotagger
Version: 1.2.2
Summary: A simple application to tag .mp3 files automatically and more.
License: MIT License
Keywords: dino,chrome,bot,game,automatic
Author: Juan Rivero Sesma
Author-email: jriverosesma@gmail.com
Requires-Python: >=3.10
Classifier: Programming Language :: Python :: 3
Classifier: Operating System :: OS Independent
Provides-Extra: dev
Requires-Dist: black (>=25.1.0,<26.0.0) ; extra == "dev"
Requires-Dist: bumpver (>=2024.1130,<2025.0) ; extra == "dev"
Requires-Dist: flake8 (>=7.2.0,<8.0.0) ; extra == "dev"
Requires-Dist: isort (>=6.0.1,<7.0.0) ; extra == "dev"
Requires-Dist: mutagen (>=1.47.0,<2.0.0)
Requires-Dist: pillow (>=10.4.0,<11.0.0) ; extra == "dev"
Requires-Dist: pre-commit (>=4.2.0,<5.0.0) ; extra == "dev"
Requires-Dist: pyqt5 (>=5.15.9,<6.0.0)
Requires-Dist: pyqt5-tools (>=5.15.9.3.3,<6.0.0.0.0) ; extra == "dev"
Requires-Dist: pytest (>=7.4.4,<8.0.0) ; extra == "dev"
Requires-Dist: pytest-mock (>=3.14.1,<4.0.0) ; extra == "dev"
Requires-Dist: pytest-sugar (>=0.9.7,<0.10.0) ; extra == "dev"
Requires-Dist: requests (>=2.32.3,<3.0.0)
Requires-Dist: shazamio (>=0.8.0,<0.9.0)
Requires-Dist: validators (>=0.35.0,<0.36.0)
Requires-Dist: yt-dlp (>=2025.5.22)
Project-URL: Homepage, https://github.com/jriverosesma/mp3-autotagger
Project-URL: Issue Tracker, https://github.com/jriverosesma/mp3-autotagger/issues
